<?xml version="1.0" encoding="UTF-8"?><record_update table="item_option_new">
    <item_option_new action="DELETE">
        <active>true</active>
        <attributes/>
        <cat_item display_value="YubiKey 5NFC">6c7d4d3e1b700110b72e99f7b04bcbf6</cat_item>
        <category/>
        <choice_direction>down</choice_direction>
        <choice_field/>
        <choice_table/>
        <create_roles/>
        <default_html_value/>
        <default_value/>
        <delete_roles/>
        <delivery_plan/>
        <description/>
        <display_title>false</display_title>
        <do_not_select_first>false</do_not_select_first>
        <dynamic_default_value/>
        <dynamic_ref_qual/>
        <enable_also_request_for>false</enable_also_request_for>
        <example_text/>
        <field/>
        <global>false</global>
        <help_tag>More information</help_tag>
        <help_text/>
        <hidden>true</hidden>
        <include_none>false</include_none>
        <instructions/>
        <layout>normal</layout>
        <list_table/>
        <lookup_label/>
        <lookup_price/>
        <lookup_table/>
        <lookup_unique>false</lookup_unique>
        <lookup_value/>
        <macro/>
        <macroponent/>
        <mandatory>false</mandatory>
        <map_to_field>false</map_to_field>
        <mask_use_confirmation>false</mask_use_confirmation>
        <mask_use_encryption>false</mask_use_encryption>
        <name>yubikey_product_id</name>
        <order>200</order>
        <price_if_checked>0</price_if_checked>
        <pricing_implications>false</pricing_implications>
        <published_ref display_value="YubiKey Product ID">b247f87e1b300110b72e99f7b04bcb0f</published_ref>
        <question_text>YubiKey Product ID</question_text>
        <read_only>false</read_only>
        <read_roles/>
        <read_script/>
        <rec_lookup_price/>
        <rec_price_if_checked>0</rec_price_if_checked>
        <record/>
        <record_producer_table/>
        <reference/>
        <reference_qual>undefined</reference_qual>
        <reference_qual_condition>undefined</reference_qual_condition>
        <rich_text/>
        <roles_to_use_also_request_for/>
        <save_script/>
        <scale_max>5</scale_max>
        <scale_min>0</scale_min>
        <show_help>false</show_help>
        <show_help_on_load>false</show_help_on_load>
        <sp_widget/>
        <summary_macro/>
        <sys_class_name>item_option_new</sys_class_name>
        <sys_created_by>admin</sys_created_by>
        <sys_created_on>2022-01-05 21:11:49</sys_created_on>
        <sys_id>ac7d81321bb00110b72e99f7b04bcb43</sys_id>
        <sys_mod_count>0</sys_mod_count>
        <sys_name>YubiKey Product ID</sys_name>
        <sys_package display_value="Yubico Enterprise Delivery API Spoke" source="x_703594_yubico_en">94763c3e1b300110b72e99f7b04bcbca</sys_package>
        <sys_policy/>
        <sys_scope display_value="Yubico Enterprise Delivery API Spoke">94763c3e1b300110b72e99f7b04bcbca</sys_scope>
        <sys_update_name>item_option_new_ac7d81321bb00110b72e99f7b04bcb43</sys_update_name>
        <sys_updated_by>admin</sys_updated_by>
        <sys_updated_on>2022-01-05 21:11:49</sys_updated_on>
        <table/>
        <tooltip/>
        <type>3</type>
        <ui_page/>
        <unique>false</unique>
        <use_dynamic_default>false</use_dynamic_default>
        <use_reference_qualifier>simple</use_reference_qualifier>
        <validate_regex/>
        <variable_name/>
        <variable_set/>
        <variable_width/>
        <visibility>1</visibility>
        <visible_bundle>true</visible_bundle>
        <visible_guide>true</visible_guide>
        <visible_standalone>true</visible_standalone>
        <visible_summary>true</visible_summary>
        <write_roles/>
    </item_option_new>
    <sys_translated_text action="DELETE" query="documentkey=ac7d81321bb00110b72e99f7b04bcb43"/>
    <fx_price action="DELETE" query="id=ac7d81321bb00110b72e99f7b04bcb43"/>
    <fx_price action="DELETE">
        <amount>0</amount>
        <currency display_value="USD">USD</currency>
        <field>price_if_checked</field>
        <id>ac7d81321bb00110b72e99f7b04bcb43</id>
        <parent/>
        <reference_amount>0</reference_amount>
        <reference_currency display_value="USD">USD</reference_currency>
        <sys_created_by>admin</sys_created_by>
        <sys_created_on>2022-01-05 21:11:49</sys_created_on>
        <sys_id>e47d81321bb00110b72e99f7b04bcb47</sys_id>
        <sys_mod_count>0</sys_mod_count>
        <sys_updated_by>admin</sys_updated_by>
        <sys_updated_on>2022-01-05 21:11:49</sys_updated_on>
        <table>item_option_new</table>
        <type>calculated</type>
    </fx_price>
    <fx_price action="DELETE">
        <amount>0</amount>
        <currency display_value="USD">USD</currency>
        <field>rec_price_if_checked</field>
        <id>ac7d81321bb00110b72e99f7b04bcb43</id>
        <parent/>
        <reference_amount>0</reference_amount>
        <reference_currency display_value="USD">USD</reference_currency>
        <sys_created_by>admin</sys_created_by>
        <sys_created_on>2022-01-05 21:11:49</sys_created_on>
        <sys_id>a87d81321bb00110b72e99f7b04bcb46</sys_id>
        <sys_mod_count>0</sys_mod_count>
        <sys_updated_by>admin</sys_updated_by>
        <sys_updated_on>2022-01-05 21:11:49</sys_updated_on>
        <table>item_option_new</table>
        <type>calculated</type>
    </fx_price>
    <sys_update_version action="INSERT_OR_UPDATE">
        <action>DELETE</action>
        <application display_value="Yubico Enterprise Delivery API Spoke">94763c3e1b300110b72e99f7b04bcbca</application>
        <file_path/>
        <instance_id>4acda43c1b887810e84d2f8dee4bcb8b</instance_id>
        <instance_name>dev114096</instance_name>
        <name>item_option_new_ac7d81321bb00110b72e99f7b04bcb43</name>
        <payload><![CDATA[<?xml version="1.0" encoding="UTF-8"?><record_update table="item_option_new"><item_option_new action="INSERT_OR_UPDATE"><active>true</active><attributes/><cat_item display_value="YubiKey 5NFC">6c7d4d3e1b700110b72e99f7b04bcbf6</cat_item><category/><choice_direction>down</choice_direction><choice_field/><choice_table/><create_roles/><default_html_value/><default_value/><delete_roles/><delivery_plan/><description/><display_title>false</display_title><do_not_select_first>false</do_not_select_first><dynamic_default_value/><dynamic_ref_qual/><enable_also_request_for>false</enable_also_request_for><example_text/><field/><global>false</global><help_tag>More information</help_tag><help_text/><hidden>true</hidden><include_none>false</include_none><instructions/><layout>normal</layout><list_table/><lookup_label/><lookup_price/><lookup_table/><lookup_unique>false</lookup_unique><lookup_value/><macro/><macroponent/><mandatory>false</mandatory><map_to_field>false</map_to_field><mask_use_confirmation>false</mask_use_confirmation><mask_use_encryption>false</mask_use_encryption><name>yubikey_product_id</name><order>200</order><price_if_checked>0</price_if_checked><pricing_implications>false</pricing_implications><published_ref display_value="YubiKey Product ID">b247f87e1b300110b72e99f7b04bcb0f</published_ref><question_text>YubiKey Product ID</question_text><read_only>false</read_only><read_roles/><read_script/><rec_lookup_price/><rec_price_if_checked>0</rec_price_if_checked><record/><record_producer_table/><reference/><reference_qual>undefined</reference_qual><reference_qual_condition>undefined</reference_qual_condition><rich_text/><roles_to_use_also_request_for/><save_script/><scale_max>5</scale_max><scale_min>0</scale_min><show_help>false</show_help><show_help_on_load>false</show_help_on_load><sp_widget/><summary_macro/><sys_class_name>item_option_new</sys_class_name><sys_created_by>admin</sys_created_by><sys_created_on>2022-01-05 21:11:49</sys_created_on><sys_id>ac7d81321bb00110b72e99f7b04bcb43</sys_id><sys_mod_count>0</sys_mod_count><sys_name>YubiKey Product ID</sys_name><sys_package display_value="Yubico Enterprise Delivery API Spoke" source="x_703594_yubico_en">94763c3e1b300110b72e99f7b04bcbca</sys_package><sys_policy/><sys_scope display_value="Yubico Enterprise Delivery API Spoke">94763c3e1b300110b72e99f7b04bcbca</sys_scope><sys_update_name>item_option_new_ac7d81321bb00110b72e99f7b04bcb43</sys_update_name><sys_updated_by>admin</sys_updated_by><sys_updated_on>2022-01-05 21:11:49</sys_updated_on><table/><tooltip/><type>3</type><ui_page/><unique>false</unique><use_dynamic_default>false</use_dynamic_default><use_reference_qualifier>simple</use_reference_qualifier><validate_regex/><variable_name/><variable_set/><variable_width/><visibility>1</visibility><visible_bundle>true</visible_bundle><visible_guide>true</visible_guide><visible_standalone>true</visible_standalone><visible_summary>true</visible_summary><write_roles/></item_option_new><sys_translated_text action="delete_multiple" query="documentkey=ac7d81321bb00110b72e99f7b04bcb43"/><fx_price action="delete_multiple" query="id=ac7d81321bb00110b72e99f7b04bcb43"/><fx_price action="INSERT_OR_UPDATE"><amount>0</amount><currency display_value="USD">USD</currency><field>price_if_checked</field><id>ac7d81321bb00110b72e99f7b04bcb43</id><parent/><reference_amount>0</reference_amount><reference_currency display_value="USD">USD</reference_currency><sys_created_by>admin</sys_created_by><sys_created_on>2022-01-05 21:11:49</sys_created_on><sys_id>e47d81321bb00110b72e99f7b04bcb47</sys_id><sys_mod_count>0</sys_mod_count><sys_updated_by>admin</sys_updated_by><sys_updated_on>2022-01-05 21:11:49</sys_updated_on><table>item_option_new</table><type>calculated</type></fx_price><fx_price action="INSERT_OR_UPDATE"><amount>0</amount><currency display_value="USD">USD</currency><field>rec_price_if_checked</field><id>ac7d81321bb00110b72e99f7b04bcb43</id><parent/><reference_amount>0</reference_amount><reference_currency display_value="USD">USD</reference_currency><sys_created_by>admin</sys_created_by><sys_created_on>2022-01-05 21:11:49</sys_created_on><sys_id>a87d81321bb00110b72e99f7b04bcb46</sys_id><sys_mod_count>0</sys_mod_count><sys_updated_by>admin</sys_updated_by><sys_updated_on>2022-01-05 21:11:49</sys_updated_on><table>item_option_new</table><type>calculated</type></fx_price></record_update>]]></payload>
        <payload_hash>1484352509</payload_hash>
        <record_name>YubiKey Product ID</record_name>
        <reverted_from/>
        <source>d0763c3e1b300110b72e99f7b04bcbcc</source>
        <source_table>sys_update_set</source_table>
        <state>previous</state>
        <sys_created_by>admin</sys_created_by>
        <sys_created_on>2022-01-05 21:11:49</sys_created_on>
        <sys_id>287d81321bb00110b72e99f7b04bcb4a</sys_id>
        <sys_mod_count>0</sys_mod_count>
        <sys_recorded_at>17e2c1570010000001</sys_recorded_at>
        <sys_updated_by>admin</sys_updated_by>
        <sys_updated_on>2022-01-05 21:11:49</sys_updated_on>
        <type>Variable</type>
        <update_guid>ac7d813223b001100b56ab351cca4949</update_guid>
        <update_guid_history>ac7d813223b001100b56ab351cca4949:1484352509</update_guid_history>
    </sys_update_version>
    <sys_metadata_delete action="INSERT_OR_UPDATE">
        <sys_audit_delete display_value="YubiKey Product ID">bd9d45321bb00110b72e99f7b04bcbc3</sys_audit_delete>
        <sys_class_name>sys_metadata_delete</sys_class_name>
        <sys_created_by>system</sys_created_by>
        <sys_created_on>2022-01-05 21:12:27</sys_created_on>
        <sys_db_object display_value="" name="item_option_new">item_option_new</sys_db_object>
        <sys_id>482fed381c44406a9f5d970f797d49f1</sys_id>
        <sys_metadata>ac7d81321bb00110b72e99f7b04bcb43</sys_metadata>
        <sys_mod_count>0</sys_mod_count>
        <sys_name>YubiKey Product ID</sys_name>
        <sys_package display_value="Yubico Enterprise Delivery API Spoke" source="x_703594_yubico_en">94763c3e1b300110b72e99f7b04bcbca</sys_package>
        <sys_parent display_value="">6c7d4d3e1b700110b72e99f7b04bcbf6</sys_parent>
        <sys_policy/>
        <sys_scope display_value="Yubico Enterprise Delivery API Spoke">94763c3e1b300110b72e99f7b04bcbca</sys_scope>
        <sys_scope_delete display_value="">1573c176f8c84b3998fe9a57ce7ce471</sys_scope_delete>
        <sys_update_name>item_option_new_ac7d81321bb00110b72e99f7b04bcb43</sys_update_name>
        <sys_update_version display_value="item_option_new_ac7d81321bb00110b72e99f7b04bcb43">287d81321bb00110b72e99f7b04bcb4a</sys_update_version>
        <sys_updated_by>system</sys_updated_by>
        <sys_updated_on>2022-01-05 21:12:27</sys_updated_on>
    </sys_metadata_delete>
</record_update>
